jsonplaceapi/__init__.py
jsonplaceapi/apptypes.py
jsonplaceapi/apputils.py
jsonplaceapi/main.py
jsonplaceapi/subtypes.py
jsonplaceapi-0.0.1.dist-info/LICENSE
jsonplaceapi-0.0.1.dist-info/METADATA
jsonplaceapi-0.0.1.dist-info/WHEEL
jsonplaceapi-0.0.1.dist-info/top_level.txt
jsonplaceapi-0.0.1.dist-info/RECORD
